colorizator/__init__.py
colorizator-2.1.2.dist-info/licenses/LICENSE
colorizator-2.1.2.dist-info/METADATA
colorizator-2.1.2.dist-info/WHEEL
colorizator-2.1.2.dist-info/top_level.txt
colorizator-2.1.2.dist-info/RECORD
